LICENSE.md
README.md
setup.py
cozmoai/__init__.py
cozmoai/activity.py
cozmoai/anim.py
cozmoai/anim_controller.py
cozmoai/anim_encoder.py
cozmoai/audio.py
cozmoai/behavior.py
cozmoai/brain.py
cozmoai/camera.py
cozmoai/client.py
cozmoai/conn.py
cozmoai/emotions.py
cozmoai/event.py
cozmoai/exception.py
cozmoai/filter.py
cozmoai/frame.py
cozmoai/image_encoder.py
cozmoai/json_loader.py
cozmoai/lights.py
cozmoai/logger.py
cozmoai/object.py
cozmoai/procedural_face.py
cozmoai/protocol_ast.py
cozmoai/protocol_base.py
cozmoai/protocol_declaration.py
cozmoai/protocol_encoder.py
cozmoai/protocol_generator.py
cozmoai/protocol_utils.py
cozmoai/robot.py
cozmoai/robot_debug.py
cozmoai/run.py
cozmoai/util.py
cozmoai/window.py
cozmoai/CozmoAnim/AnimClip.py
cozmoai/CozmoAnim/AnimClips.py
cozmoai/CozmoAnim/BackpackLights.py
cozmoai/CozmoAnim/BodyMotion.py
cozmoai/CozmoAnim/Event.py
cozmoai/CozmoAnim/FaceAnimation.py
cozmoai/CozmoAnim/HeadAngle.py
cozmoai/CozmoAnim/Keyframes.py
cozmoai/CozmoAnim/LiftHeight.py
cozmoai/CozmoAnim/ProceduralFace.py
cozmoai/CozmoAnim/RecordHeading.py
cozmoai/CozmoAnim/RobotAudio.py
cozmoai/CozmoAnim/TurnToRecordedHeading.py
cozmoai/CozmoAnim/__init__.py
cozmoai/audiokinetic/__init__.py
cozmoai/audiokinetic/exception.py
cozmoai/audiokinetic/soundbank.py
cozmoai/audiokinetic/soundbanksinfo.py
cozmoai/audiokinetic/wem.py
cozmoai/expressions/__init__.py
cozmoai/expressions/expressions.py
cozmoai/tests/__init__.py
cozmoai/tests/image_encoder_fixtures.py
cozmoai/tests/test_anim_encoder.py
cozmoai/tests/test_conn.py
cozmoai/tests/test_decay_graph.py
cozmoai/tests/test_frame.py
cozmoai/tests/test_image_decoder.py
cozmoai/tests/test_image_encoder.py
cozmoai/tests/test_robot_debug.py
cozmoai/tests/test_window.py
cozmoapp.egg-info/PKG-INFO
cozmoapp.egg-info/SOURCES.txt
cozmoapp.egg-info/dependency_links.txt
cozmoapp.egg-info/requires.txt
cozmoapp.egg-info/top_level.txt
tools/cozmoai_app.py
tools/cozmoai_dump.py
tools/cozmoai_replay.py
tools/cozmoai_resources.py
tools/cozmoai_update.py