Metadata-Version: 2.1
Name: cozmoapp
Version: 1.0.0
Summary: to make cozmo better
Home-page: 
Author: cozmo14047
Author-email: swest2236@gmail.com
License: MIT
Keywords: ddl,anki,cozmo,robot,robotics
Classifier: Development Status :: 4 - Beta
Classifier: License :: OSI Approved :: MIT License
Classifier: Programming Language :: Python
Classifier: Programming Language :: Python :: 3.6
Classifier: Programming Language :: Python :: 3.7
Classifier: Programming Language :: Python :: 3.8
Classifier: Programming Language :: Python :: 3.9
Classifier: Topic :: Software Development :: Libraries
Classifier: Topic :: Software Development :: Libraries :: Python Modules
Classifier: Intended Audience :: Developers
Classifier: Intended Audience :: Education
Requires-Python: >=3.6.0
License-File: LICENSE.md
Requires-Dist: dpkt
Requires-Dist: numpy
Requires-Dist: Pillow>=6.0.0
Requires-Dist: flatbuffers
